Metadata-Version: 2.1
Name: odoo-addon-website_event_filter_city
Version: 17.0.1.1.0
Requires-Python: >=3.10
Requires-Dist: odoo>=17.0a,<17.1dev
Summary: Add a customizable top area to filter events with city
Home-page: https://github.com/OCA/event
License: LGPL-3
Author: =?utf-8?q?Antiun_Ingenier=C3=ADa_S=2EL=2E=2C_Tecnativa=2C_Onestein=2C_Odoo_Community_Association_=28OCA=29?=
Author-email: support@odoo-community.org
Classifier: Programming Language :: Python
Classifier: Framework :: Odoo
Classifier: Framework :: Odoo :: 17.0
Classifier: License :: OSI Approved :: GNU Lesser General Public License v3 (LGPLv3)
